named_dataframes/__init__.py
named_dataframes/named_dataframes.py
named_dataframes-0.1.4.dist-info/WHEEL
named_dataframes-0.1.4.dist-info/METADATA
named_dataframes-0.1.4.dist-info/RECORD
