Metadata-Version: 2.1
Name: named_dataframes
Version: 0.1.4
Summary: DataFrames with names.
Home-page: UNKNOWN
License: UNKNOWN
Author: Bao Wei
Author-email: baowei.ur521@gmail.com
Requires-Dist: pandas >= 0.25
